CA Project Submission/Task C/All_CA_Labs.srcs/sources_1/new/ALUControl.v
`timescale 1ns / 1ps
// Single definition - do NOT duplicate this module anywhere else.
// ALUControl encoding:
//   0000 = SRL
//   0001 = OR
//   0010 = ADD
//   0011 = SLL
//   0110 = SUB
//   0111 = XOR
//   1000 = AND
module ALUControl (
    input  wire [1:0] ALUOp,
    input  wire [2:0] funct3,
    input  wire [6:0] funct7,
    output reg  [3:0] ALUControl
);
    wire f7b5 = funct7[5];

    always @(*) begin
        ALUControl = 4'b0010; // default: ADD

        casez ({ALUOp, funct3, f7b5})
            // ALUOp=00 : Load/Store ? ADD
            6'b00_???_?: ALUControl = 4'b0010;

            // ALUOp=01 : Branch (BEQ) ? SUB
            6'b01_???_?: ALUControl = 4'b0110;

            // ALUOp=10 : R-type
            6'b10_000_0: ALUControl = 4'b0010; // ADD
            6'b10_000_1: ALUControl = 4'b0110; // SUB
            6'b10_001_?: ALUControl = 4'b0011; // SLL
            6'b10_101_?: ALUControl = 4'b0000; // SRL
            6'b10_110_?: ALUControl = 4'b0001; // OR
            6'b10_111_?: ALUControl = 4'b1000; // AND
            6'b10_100_?: ALUControl = 4'b0111; // XOR

            // ALUOp=11 : I-type ALU (ignore funct7[5])
            6'b11_000_?: ALUControl = 4'b0010; // ADDI
            6'b11_001_?: ALUControl = 4'b0011; // SLLI
            6'b11_101_?: ALUControl = 4'b0000; // SRLI
            6'b11_110_?: ALUControl = 4'b0001; // ORI
            6'b11_111_?: ALUControl = 4'b1000; // ANDI
            6'b11_100_?: ALUControl = 4'b0111; // XORI

            default:     ALUControl = 4'b0010;
        endcase
    end
endmodule

CA_Lab09_Myrah_Romaisa/All_CA_Labs.srcs/sources_1/new/MainControl.v
`timescale 1ns / 1ps
// =========================================================
// MainControl.v
// Main Control Unit for Single-Cycle RISC-V (RV32I)
// Inputs:  opcode[6:0]
// Outputs: RegWrite, ALUSrc, MemRead, MemWrite,
//          MemtoReg, Branch, ALUOp[1:0]
// =========================================================

module MainControl (
    input  wire [6:0] opcode,
    output reg        RegWrite,
    output reg        ALUSrc,
    output reg        MemRead,
    output reg        MemWrite,
    output reg        MemtoReg,
    output reg        Branch,
    output reg [1:0]  ALUOp
);

    // RISC-V opcode definitions
    localparam R_TYPE  = 7'b0110011;  // ADD, SUB, SLL, SRL, AND, OR, XOR
    localparam I_ALU   = 7'b0010011;  // ADDI, ANDI, ORI, XORI, SLLI, SRLI
    localparam LOAD    = 7'b0000011;  // LW, LH, LB
    localparam STORE   = 7'b0100011;  // SW, SH, SB
    localparam BRANCH  = 7'b1100011;  // BEQ

    always @(*) begin
        // Safe default values (all signals de-asserted)
        RegWrite = 1'b0;
        ALUSrc   = 1'b0;
        MemRead  = 1'b0;
        MemWrite = 1'b0;
        MemtoReg = 1'b0;
        Branch   = 1'b0;
        ALUOp    = 2'b00;

        case (opcode)
            // -------------------------------------------------
            // R-type: ADD, SUB, SLL, SRL, AND, OR, XOR
            // ALU operation determined by funct3/funct7 (ALUOp=10)
            // -------------------------------------------------
            R_TYPE: begin
                RegWrite = 1'b1;
                ALUSrc   = 1'b0;  // second ALU operand from register
                MemRead  = 1'b0;
                MemWrite = 1'b0;
                MemtoReg = 1'b0;  // write ALU result to register
                Branch   = 1'b0;
                ALUOp    = 2'b10;
            end

            // -------------------------------------------------
            // I-type ALU: ADDI (and other immediate operations)
            // ALUOp=11 lets ALU control differentiate from loads
            // -------------------------------------------------
            I_ALU: begin
                RegWrite = 1'b1;
                ALUSrc   = 1'b1;  // second ALU operand from immediate
                MemRead  = 1'b0;
                MemWrite = 1'b0;
                MemtoReg = 1'b0;  // write ALU result to register
                Branch   = 1'b0;
                ALUOp    = 2'b11;
            end

            // -------------------------------------------------
            // Load: LW, LH, LB
            // ALU computes address (add), ALUOp=00
            // -------------------------------------------------
            LOAD: begin
                RegWrite = 1'b1;
                ALUSrc   = 1'b1;  // immediate as offset
                MemRead  = 1'b1;
                MemWrite = 1'b0;
                MemtoReg = 1'b1;  // write memory data to register
                Branch   = 1'b0;
                ALUOp    = 2'b00;
            end

            // -------------------------------------------------
            // Store: SW, SH, SB
            // No register write; ALU computes address (add), ALUOp=00
            // -------------------------------------------------
            STORE: begin
                RegWrite = 1'b0;
                ALUSrc   = 1'b1;  // immediate as offset
                MemRead  = 1'b0;
                MemWrite = 1'b1;
                MemtoReg = 1'b0;  // don't care - no reg write
                Branch   = 1'b0;
                ALUOp    = 2'b00;
            end

            // -------------------------------------------------
            // Branch: BEQ
            // ALU subtracts rs1-rs2 to test equality, ALUOp=01
            // -------------------------------------------------
            BRANCH: begin
                RegWrite = 1'b0;
                ALUSrc   = 1'b0;  // both operands from registers
                MemRead  = 1'b0;
                MemWrite = 1'b0;
                MemtoReg = 1'b0;  // don't care - no reg write
                Branch   = 1'b1;
                ALUOp    = 2'b01;
            end

            // -------------------------------------------------
            // Default: unknown opcode - de-assert all signals
            // -------------------------------------------------
            default: begin
                RegWrite = 1'b0;
                ALUSrc   = 1'b0;
                MemRead  = 1'b0;
                MemWrite = 1'b0;
                MemtoReg = 1'b0;
                Branch   = 1'b0;
                ALUOp    = 2'b00;
            end
        endcase
    end

endmodule

CA Project Submission/Task A/All_CA_Labs.srcs/sim_1/new/tb_lab09.v
`timescale 1ns / 1ps
// =========================================================
// tb_lab09.v
// Testbench for MainControl + ALUControl
// funct7 is full 7 bits [31:25] of the instruction
// only funct7[5] (instr bit [30]) distinguishes ADD/SUB
// =========================================================

module tb_lab09;

    reg  [6:0] opcode;
    reg  [2:0] funct3;
    reg  [6:0] funct7;   // full 7-bit funct7 [31:25]

    wire       RegWrite, ALUSrc, MemRead, MemWrite, MemtoReg, Branch;
    wire [1:0] ALUOp;
    wire [3:0] ALUControl;

    MainControl uut_main (
        .opcode   (opcode),
        .RegWrite (RegWrite),
        .ALUSrc   (ALUSrc),
        .MemRead  (MemRead),
        .MemWrite (MemWrite),
        .MemtoReg (MemtoReg),
        .Branch   (Branch),
        .ALUOp    (ALUOp)
    );

    ALUControl uut_alu (
        .ALUOp      (ALUOp),
        .funct3     (funct3),
        .funct7     (funct7),
        .ALUControl (ALUControl)
    );

    task apply_and_check;
        input [63:0] instr_name;
        input [6:0]  op;
        input [2:0]  f3;
        input [6:0]  f7;   // full 7-bit funct7
        input        exp_RegWrite, exp_ALUSrc, exp_MemRead, exp_MemWrite;
        input        exp_MemtoReg, exp_Branch;
        input [1:0]  exp_ALUOp;
        input [3:0]  exp_ALUCtrl;
        begin
            opcode = op;
            funct3 = f3;
            funct7 = f7;
            #10;

            $display("-----------------------------------------------");
            $display(" Instruction : %s", instr_name);
            $display(" opcode=%b  funct3=%b  funct7=%b", opcode, funct3, funct7);
            $display(" RegWrite=%b ALUSrc=%b MemRead=%b MemWrite=%b MemtoReg=%b Branch=%b",
                      RegWrite, ALUSrc, MemRead, MemWrite, MemtoReg, Branch);
            $display(" ALUOp=%b  ALUControl=%b", ALUOp, ALUControl);

            if (RegWrite   !== exp_RegWrite)  $display("  [FAIL] RegWrite  : got %b, exp %b", RegWrite,   exp_RegWrite);
            if (ALUSrc     !== exp_ALUSrc)    $display("  [FAIL] ALUSrc    : got %b, exp %b", ALUSrc,     exp_ALUSrc);
            if (MemRead    !== exp_MemRead)   $display("  [FAIL] MemRead   : got %b, exp %b", MemRead,    exp_MemRead);
            if (MemWrite   !== exp_MemWrite)  $display("  [FAIL] MemWrite  : got %b, exp %b", MemWrite,   exp_MemWrite);
            if (Branch     !== exp_Branch)    $display("  [FAIL] Branch    : got %b, exp %b", Branch,     exp_Branch);
            if (ALUOp      !== exp_ALUOp)     $display("  [FAIL] ALUOp     : got %b, exp %b", ALUOp,      exp_ALUOp);
            if (ALUControl !== exp_ALUCtrl)   $display("  [FAIL] ALUControl: got %b, exp %b", ALUControl, exp_ALUCtrl);
            else $display("  [PASS]");
        end
    endtask

    initial begin
        $dumpfile("tb_lab09.vcd");
        $dumpvars(0, tb_lab09);

        // Initialize all inputs to avoid X state at t=0
        opcode = 7'b0;
        funct3 = 3'b0;
        funct7 = 7'b0;
        #5;

        $display("=== RISC-V Control Path Testbench ===");

        // --------------------------------------------------
        // R-type (opcode=0110011)
        // funct7=0000000 for ADD,SLL,SRL,AND,OR,XOR
        // funct7=0100000 for SUB (bit[5]=1)
        // --------------------------------------------------
        apply_and_check("ADD ",  7'b0110011, 3'b000, 7'b0000000,  1,0,0,0, 0,0, 2'b10, 4'b0010);
        apply_and_check("SUB ",  7'b0110011, 3'b000, 7'b0100000,  1,0,0,0, 0,0, 2'b10, 4'b0110);
        apply_and_check("SLL ",  7'b0110011, 3'b001, 7'b0000000,  1,0,0,0, 0,0, 2'b10, 4'b0011);
        apply_and_check("SRL ",  7'b0110011, 3'b101, 7'b0000000,  1,0,0,0, 0,0, 2'b10, 4'b0000);
        apply_and_check("AND ",  7'b0110011, 3'b111, 7'b0000000,  1,0,0,0, 0,0, 2'b10, 4'b1000);
        apply_and_check("OR  ",  7'b0110011, 3'b110, 7'b0000000,  1,0,0,0, 0,0, 2'b10, 4'b0001);
        apply_and_check("XOR ",  7'b0110011, 3'b100, 7'b0000000,  1,0,0,0, 0,0, 2'b10, 4'b0111);

        // --------------------------------------------------
        // I-type ALU (opcode=0010011)
        // funct7 is part of the immediate, use 0000000
        // --------------------------------------------------
        apply_and_check("ADDI",  7'b0010011, 3'b000, 7'b0000000,  1,1,0,0, 0,0, 2'b11, 4'b0010);

        // --------------------------------------------------
        // Load (opcode=0000011)
        // funct7 not used, always 0000000
        // --------------------------------------------------
        apply_and_check("LW  ",  7'b0000011, 3'b010, 7'b0000000,  1,1,1,0, 1,0, 2'b00, 4'b0010);
        apply_and_check("LH  ",  7'b0000011, 3'b001, 7'b0000000,  1,1,1,0, 1,0, 2'b00, 4'b0010);
        apply_and_check("LB  ",  7'b0000011, 3'b000, 7'b0000000,  1,1,1,0, 1,0, 2'b00, 4'b0010);

        // --------------------------------------------------
        // Store (opcode=0100011)
        // funct7 not used, always 0000000
        // --------------------------------------------------
        apply_and_check("SW  ",  7'b0100011, 3'b010, 7'b0000000,  0,1,0,1, 0,0, 2'b00, 4'b0010);
        apply_and_check("SH  ",  7'b0100011, 3'b001, 7'b0000000,  0,1,0,1, 0,0, 2'b00, 4'b0010);
        apply_and_check("SB  ",  7'b0100011, 3'b000, 7'b0000000,  0,1,0,1, 0,0, 2'b00, 4'b0010);

        // --------------------------------------------------
        // Branch (opcode=1100011)
        // funct7 not used, always 0000000
        // --------------------------------------------------
        apply_and_check("BEQ ",  7'b1100011, 3'b000, 7'b0000000,  0,0,0,0, 0,1, 2'b01, 4'b0110);

        $display("=== Testbench complete ===");
        $finish;
    end

endmodule

CA Project Submission/Task C/All_CA_Labs.sim/sim_1/behav/xsim/tb_lab09.vcd
$date
   Thu Mar 26 11:24:22 2026
$end
$version
  2020.1
$end
$timescale
  1ps
$end
$scope module tb_lab09 $end
$var reg 7 ! opcode [6:0] $end
$var reg 3 " funct3 [2:0] $end
$var reg 7 # funct7 [6:0] $end
$var wire 1 $ RegWrite $end
$var wire 1 % ALUSrc $end
$var wire 1 & MemRead $end
$var wire 1 ' MemWrite $end
$var wire 1 ( MemtoReg $end
$var wire 1 ) Branch $end
$var wire 2 * ALUOp [1:0] $end
$var wire 4 + ALUControl [3:0] $end
$scope module uut_main $end
$var wire 7 , opcode [6:0] $end
$var reg 1 - RegWrite $end
$var reg 1 . ALUSrc $end
$var reg 1 / MemRead $end
$var reg 1 0 MemWrite $end
$var reg 1 1 MemtoReg $end
$var reg 1 2 Branch $end
$var reg 2 3 ALUOp [1:0] $end
$var parameter 7 4 R_TYPE [6:0] $end
$var parameter 7 5 I_ALU [6:0] $end
$var parameter 7 6 LOAD [6:0] $end
$var parameter 7 7 STORE [6:0] $end
$var parameter 7 8 BRANCH [6:0] $end
$upscope $end
$scope module uut_alu $end
$var wire 2 * ALUOp [1:0] $end
$var wire 3 9 funct3 [2:0] $end
$var wire 7 : funct7 [6:0] $end
$var reg 4 ; ALUControl [3:0] $end
$var wire 1 < f7b5 $end
$upscope $end
$scope task apply_and_check $end
$var reg 64 = instr_name [63:0] $end
$var reg 7 > op [6:0] $end
$var reg 3 ? f3 [2:0] $end
$var reg 7 @ f7 [6:0] $end
$var reg 1 A exp_RegWrite $end
$var reg 1 B exp_ALUSrc $end
$var reg 1 C exp_MemRead $end
$var reg 1 D exp_MemWrite $end
$var reg 1 E exp_MemtoReg $end
$var reg 1 F exp_Branch $end
$var reg 2 G exp_ALUOp [1:0] $end
$var reg 4 H exp_ALUCtrl [3:0] $end
$upscope $end
$upscope $end
$enddefinitions $end
#0
$dumpvars
b0 !
b0 "
b0 #
0$
0%
0&
0'
0(
0)
b0 *
b10 +
b0 ,
0-
0.
0/
00
01
02
b0 3
b110011 4
b10011 5
b11 6
b100011 7
b1100011 8
b0 9
b0 :
b10 ;
0<
bx =
bx >
bx ?
bx @
xA
xB
xC
xD
xE
xF
bx G
bx H
$end
#5000
b110011 !
b0 "
b0 #
1$
b10 *
b110011 ,
1-
0.
0/
00
01
02
b10 3
b10 ;
b1000001010001000100010000100000 =
b110011 >
b0 ?
b0 @
1A
0B
0C
0D
0E
0F
b10 G
b10 H
#15000
b110011 !
b0 "
b100000 #
b110 +
b100000 :
b110 ;
1<
b1010011010101010100001000100000 =
b100000 @
b110 H
#25000
b110011 !
b1 "
b0 #
b11 +
b1 9
b0 :
b11 ;
0<
b1010011010011000100110000100000 =
b1 ?
b0 @
b11 H
#35000
b110011 !
b101 "
b0 #
b0 +
b101 9
b0 ;
b1010011010100100100110000100000 =
b101 ?
b0 H
#45000
b110011 !
b111 "
b0 #
b1000 +
b111 9
b1000 ;
b1000001010011100100010000100000 =
b111 ?
b1000 H
#55000
b110011 !
b110 "
b0 #
b1 +
b110 9
b1 ;
b1001111010100100010000000100000 =
b110 ?
b1 H
#65000
b110011 !
b100 "
b0 #
b111 +
b100 9
b111 ;
b1011000010011110101001000100000 =
b100 ?
b111 H
#75000
b10011 !
b0 "
b0 #
1%
b11 *
b10 +
b10011 ,
1-
1.
0/
00
01
02
b11 3
b0 9
b10 ;
b1000001010001000100010001001001 =
b10011 >
b0 ?
1B
b11 G
b10 H
#85000
b11 !
b10 "
b0 #
1&
1(
b0 *
b11 ,
1-
1.
1/
00
11
02
b0 3
b10 9
b10 ;
b1001100010101110010000000100000 =
b11 >
b10 ?
1C
1E
b0 G
#95000
b11 !
b1 "
b0 #
b1 9
b10 ;
b1001100010010000010000000100000 =
b1 ?
#105000
b11 !
b0 "
b0 #
b0 9
b10 ;
b1001100010000100010000000100000 =
b0 ?
#115000
b100011 !
b10 "
b0 #
0$
0&
1'
0(
b100011 ,
0-
1.
0/
10
01
02
b0 3
b10 9
b10 ;
b1010011010101110010000000100000 =
b100011 >
b10 ?
0A
0C
1D
0E
#125000
b100011 !
b1 "
b0 #
b1 9
b10 ;
b1010011010010000010000000100000 =
b1 ?
#135000
b100011 !
b0 "
b0 #
b0 9
b10 ;
b1010011010000100010000000100000 =
b0 ?
#145000
b1100011 !
b0 "
b0 #
0%
0'
1)
b1 *
b110 +
b1100011 ,
0-
0.
0/
00
01
12
b1 3
b110 ;
b1000010010001010101000100100000 =
b1100011 >
0B
0D
1F
b1 G
b110 H
