CA_Lab11_Myrah_Romaisa/All_CA_Labs.srcs/sources_1/new/mux2.v

`timescale 1ns / 1ps

module mux2 (
    input  [31:0] in0,
    input  [31:0] in1,
    input         sel,
    output [31:0] out
);
    assign out = sel ? in1 : in0;
endmodule

CA Project Submission/Task B/All_CA_Labs.srcs/sources_1/new/branchAdder.v


`timescale 1ns / 1ps
// immGen already encodes B-type with imm[0]=0,
// we just add directly
module branchAdder (
    input  [31:0] PC,
    input  [31:0] imm,
    output [31:0] branchTarget
);
    assign branchTarget = PC + imm;
endmodule

CA Project Submission/Task C/All_CA_Labs.srcs/sources_1/new/immGen.v
//=======================TASK B=============================

`timescale 1ns / 1ps
// immGen - Immediate Generator
// Supports: I-type, S-type, B-type, J-type, U-type (LUI)
module immGen (
    input  [31:0] instruction,
    output reg [31:0] imm
);
    wire [6:0] opcode = instruction[6:0];

    always @(*) begin
        case (opcode)
            // I-type: ADDI, ANDI, ORI, XORI, SLLI, SRLI, LW, LH, LB
            7'b0010011,
            7'b0000011:
                imm = {{20{instruction[31]}}, instruction[31:20]};

            // JALR (I-type)
            7'b1100111:
                imm = {{20{instruction[31]}}, instruction[31:20]};

            // S-type: SW, SH, SB
            7'b0100011:
                imm = {{20{instruction[31]}},
                        instruction[31:25],
                        instruction[11:7]};

            // B-type: BEQ, BNE, BGE
            // imm[0] hardwired to 0
            7'b1100011:
                imm = {{19{instruction[31]}},
                        instruction[31],
                        instruction[7],
                        instruction[30:25],
                        instruction[11:8],
                        1'b0};

            // J-type: JAL
            // imm[0] hardwired to 0
            7'b1101111:
                imm = {{12{instruction[31]}},
                        instruction[19:12],
                        instruction[20],
                        instruction[30:21],
                        1'b0};

            // U-type: LUI
            // upper 20 bits, lower 12 bits zero
            7'b0110111:
                imm = {instruction[31:12], 12'b0};

            default:
                imm = 32'b0;
        endcase
    end
endmodule

CA_Lab11_Myrah_Romaisa/All_CA_Labs.srcs/sources_1/new/pcAdder.v
`timescale 1ns / 1ps
module pcAdder (
    input  [31:0] PC,
    output [31:0] PCplus4
);
    assign PCplus4 = PC + 32'd4;
endmodule

CA_Lab11_Myrah_Romaisa/All_CA_Labs.srcs/sources_1/new/ProgramCounter.v
module ProgramCounter (
    input        clk,
    input        rst,
    input  [31:0] nextPC,
    output reg [31:0] PC
);
    always @(posedge clk or posedge rst) begin
        if (rst)
            PC <= 32'b0;
        else
            PC <= nextPC;
    end
endmodule

CA Project Submission/Task A/All_CA_Labs.srcs/sim_1/new/tb_lab11_task1.v
`timescale 1ns/1ps

module tb_lab11_task1;

    reg        clk, rst, PCSrc;
    reg [31:0] instruction;
    wire [31:0] PC, PCplus4, branchTarget, nextPC, imm;

    // Instantiate all modules
    ProgramCounter  u_pc   (.clk(clk), .rst(rst), .nextPC(nextPC), .PC(PC));
    pcAdder         u_pca  (.PC(PC), .PCplus4(PCplus4));
    immGen          u_imm  (.instruction(instruction), .imm(imm));
    branchAdder     u_ba   (.PC(PC), .imm(imm), .branchTarget(branchTarget));
    mux2            u_mux  (.in0(PCplus4), .in1(branchTarget), .sel(PCSrc), .out(nextPC));

    // Clock: 10ns period
    initial clk = 0;
    always #5 clk = ~clk;

    initial begin
        $dumpfile("tb_lab11_task1.vcd");
        $dumpvars(0, tb_lab11_task1);

        // ---- Reset ----
        rst = 1; PCSrc = 0;
        instruction = 32'b0;
        @(posedge clk); #1;
        rst = 0;

        // ---- Test 1: Sequential execution (PCSrc=0, PC should go 0,4,8,12) ----
        repeat(4) @(posedge clk);
        $display("PC after 4 cycles (expect 16): %0d", PC);

        // ---- Test 2: I-type immediate (addi x1, x0, 5)  expect imm=5 ----
        // addi opcode=0010011, rd=00001, funct3=000, rs1=00000, imm=000000000101
        instruction = 32'b000000000101_00000_000_00001_0010011;
        #1;
        $display("I-type imm (expect 5): %0d", $signed(imm));

        // ---- Test 3: I-type negative (addi x1, x0, -3)  expect imm=-3 ----
        instruction = 32'b111111111101_00000_000_00001_0010011;
        #1;
        $display("I-type imm (expect -3): %0d", $signed(imm));

        // ---- Test 4: S-type immediate (sw x1, 8(x2))  expect imm=8 ----
        // imm[11:5]=0000000, imm[4:0]=01000
        instruction = 32'b0000000_00001_00010_010_01000_0100011;
        #1;
        $display("S-type imm (expect 8): %0d", $signed(imm));

        // ---- Test 5: B-type immediate (beq x0,x0, +4)  expect imm=4 ----
        // offset=4 bytes ? encoded imm = 2 (hardware shifts left by 1)
        // imm[12]=0,imm[11]=0,imm[10:5]=000001,imm[4:1]=0000
        instruction = 32'b0_000001_00000_00000_000_0000_0_1100011;
        #1;
        $display("B-type imm (expect 4): %0d", $signed(imm));

        // ---- Test 6: Branch taken (PCSrc=1), check branchTarget ----
        rst = 1; @(posedge clk); #1; rst = 0;   // reset PC to 0
        // beq with offset +10 bytes ? imm=10
        instruction = 32'b0_000010_00000_00000_000_1010_0_1100011;
        #2;
        PCSrc = 1;
        @(posedge clk); #1;
        $display("PC after branch taken (expect 10): %0d", PC);

        $finish;
    end
endmodule

CA Project Submission/Task C/All_CA_Labs.sim/sim_1/behav/xsim/tb_lab11_task1.vcd
$date
   Mon Apr 13 02:10:50 2026
$end
$version
  2020.1
$end
$timescale
  1ps
$end
$scope module tb_lab11_task1 $end
$var reg 1 ! clk $end
$var reg 1 " rst $end
$var reg 1 # PCSrc $end
$var reg 32 $ instruction [31:0] $end
$var wire 32 % PC [31:0] $end
$var wire 32 & PCplus4 [31:0] $end
$var wire 32 ' branchTarget [31:0] $end
$var wire 32 ( nextPC [31:0] $end
$var wire 32 ) imm [31:0] $end
$scope module u_pc $end
$var wire 1 * clk $end
$var wire 1 + rst $end
$var wire 32 ( nextPC [31:0] $end
$var reg 32 , PC [31:0] $end
$upscope $end
$scope module u_pca $end
$var wire 32 % PC [31:0] $end
$var wire 32 & PCplus4 [31:0] $end
$upscope $end
$scope module u_imm $end
$var wire 32 - instruction [31:0] $end
$var reg 32 . imm [31:0] $end
$var wire 7 / opcode [6:0] $end
$upscope $end
$scope module u_ba $end
$var wire 32 % PC [31:0] $end
$var wire 32 ) imm [31:0] $end
$var wire 32 ' branchTarget [31:0] $end
$upscope $end
$scope module u_mux $end
$var wire 32 & in0 [31:0] $end
$var wire 32 ' in1 [31:0] $end
$var wire 1 0 sel $end
$var wire 32 ( out [31:0] $end
$upscope $end
$upscope $end
$enddefinitions $end
#0
$dumpvars
0!
1"
0#
b0 $
b0 %
b100 &
b0 '
b100 (
b0 )
0*
1+
b0 ,
b0 -
b0 .
b0 /
00
$end
#5000
1!
1*
#6000
0"
0+
#10000
0!
0*
#15000
1!
b100 %
b1000 &
b100 '
b1000 (
1*
b100 ,
#20000
0!
0*
#25000
1!
b1000 %
b1100 &
b1000 '
b1100 (
1*
b1000 ,
#30000
0!
0*
#35000
1!
b1100 %
b10000 &
b1100 '
b10000 (
1*
b1100 ,
#40000
0!
0*
#45000
1!
b10100000000000010010011 $
b10000 %
b10100 &
b11010 '
b10100 (
b101 )
1*
b10000 ,
b10100000000000010010011 -
b101 .
b10011 /
#46000
b11111111110100000000000010010011 $
b1010 '
b11111111111111111111111111111101 )
b11111111110100000000000010010011 -
b11111111111111111111111111111101 .
#47000
b100010010010000100011 $
b100000 '
b1000 )
b100010010010000100011 -
b1000 .
b100011 /
#48000
b10000000000000000001100011 $
b1010000 '
b100000 )
b10000000000000000001100011 -
b100000 .
b1100011 /
#49000
1"
b0 %
b100 &
b1000000 '
b100 (
1+
b0 ,
#50000
0!
0*
#55000
1!
1*
#56000
0"
b100000000000000101001100011 $
b10101000 '
b1010100 )
0+
b100000000000000101001100011 -
b1010100 .
#58000
1#
b10101000 (
10
